proxi_flat_cpp.so
proxi_knn_cpp.so
proxi_pca_cpp.so
proxiss/ProxiFlat.py
proxiss/ProxiKNN.py
proxiss/ProxiPCA.py
proxiss/__init__.py
proxiss.libs/libomp-e26f7e59.so.5
proxiss-0.4.1.dist-info/METADATA
proxiss-0.4.1.dist-info/WHEEL
proxiss-0.4.1.dist-info/RECORD
proxiss-0.4.1.dist-info/licenses/LICENSE.txt
proxiss-0.4.1.dist-info/sboms/auditwheel.cdx.json
