Metadata-Version: 2.2
Name: proxiss
Version: 0.4.1
Summary: Proxiss: Accelerating nearest-neighbor search for high-dimensional data!
Author-Email: Siddhant Biradar <siddhant.biradar.pes@gmail.com>
License: LICENSE
Classifier: Development Status :: 3 - Alpha
Classifier: Intended Audience :: Developers
Classifier: Intended Audience :: Science/Research
Classifier: Programming Language :: Python :: 3
Classifier: Programming Language :: Python :: 3.10
Classifier: Programming Language :: Python :: 3.11
Classifier: Programming Language :: Python :: 3.12
Classifier: Programming Language :: Python :: 3.13
Classifier: Programming Language :: C++
Classifier: Topic :: Scientific/Engineering
Classifier: Topic :: Scientific/Engineering :: Artificial Intelligence
Classifier: Topic :: Software Development :: Libraries :: Python Modules
Requires-Python: >=3.9
Requires-Dist: numpy>=1.20
Requires-Dist: ply
Requires-Dist: six
Requires-Dist: scipy
Requires-Dist: sympy==1.14.0
Requires-Dist: scikit-build-core>=0.11.5
Requires-Dist: pytest>=8.4.1
